pygermanet/__init__.py
pygermanet/baseforms_by_projekt_deutscher_wortschatz.txt.gz
pygermanet/germanet.py
pygermanet/mongo_import.py
pygermanet/sdewac-gn-words.tsv.gz
pygermanet/VERSION
pygermanet-1.0.2.dist-info/DESCRIPTION.rst
pygermanet-1.0.2.dist-info/METADATA
pygermanet-1.0.2.dist-info/metadata.json
pygermanet-1.0.2.dist-info/RECORD
pygermanet-1.0.2.dist-info/top_level.txt
pygermanet-1.0.2.dist-info/WHEEL
