Metadata-Version: 2.0
Name: pygermanet
Version: 1.0.2
Summary: GermaNet API for Python
Home-page: https://github.com/wroberts/pygermanet
Author: Will Roberts
Author-email: wildwilhelm@gmail.com
License: MIT
Keywords: germanet nlp wordnet
Platform: UNKNOWN
Classifier: Development Status :: 4 - Beta
Classifier: Intended Audience :: Developers
Classifier: Intended Audience :: Science/Research
Classifier: Natural Language :: German
Classifier: Topic :: Scientific/Engineering
Classifier: Topic :: Text Processing :: Linguistic
Classifier: License :: OSI Approved :: MIT License
Classifier: Programming Language :: Python :: 2
Classifier: Programming Language :: Python :: 2.7
Classifier: Programming Language :: Python :: 3
Classifier: Programming Language :: Python :: 3.2
Classifier: Programming Language :: Python :: 3.3
Classifier: Programming Language :: Python :: 3.4
Requires-Dist: pymongo
Requires-Dist: future (>=0.14)
